Metadata-Version: 2.1
Name: my-package-ani
Version: 1
Summary: AssignmentQs2
Home-page: https://github.com/anime-sh/SE_Lab_Python_DS_Assignment/tree/master/AssignmentQs2
Author: AJ
License: UNKNOWN
Platform: UNKNOWN
Classifier: Programming Language :: Python :: 3
Classifier: License :: OSI Approved :: MIT License
Classifier: Operating System :: OS Independent
Requires-Python: >=3.6
